imio.zamqp.pm-0.19-py3.12-nspkg.pth
imio/zamqp/pm/__init__.py
imio/zamqp/pm/configure.zcml
imio/zamqp/pm/consumer.py
imio/zamqp/pm/interfaces.py
imio/zamqp/pm/overrides.py
imio/zamqp/pm/overrides.zcml
imio/zamqp/pm/profiles.zcml
imio/zamqp/pm/setuphandlers.py
imio/zamqp/pm/testing.py
imio/zamqp/pm/testing.zcml
imio/zamqp/pm/utils.py
imio/zamqp/pm/browser/__init__.py
imio/zamqp/pm/browser/configure.zcml
imio/zamqp/pm/browser/overrides.py
imio/zamqp/pm/browser/views.py
imio/zamqp/pm/browser/static/barcode.png
imio/zamqp/pm/locales/imio.history.pot
imio/zamqp/pm/locales/imio.zamqp.pm.pot
imio/zamqp/pm/locales/plone.pot
imio/zamqp/pm/locales/sync_pos.sh
imio/zamqp/pm/locales/en/LC_MESSAGES/imio.history.po
imio/zamqp/pm/locales/en/LC_MESSAGES/imio.zamqp.pm.po
imio/zamqp/pm/locales/en/LC_MESSAGES/plone.po
imio/zamqp/pm/locales/fr/LC_MESSAGES/imio.history.po
imio/zamqp/pm/locales/fr/LC_MESSAGES/imio.zamqp.pm.po
imio/zamqp/pm/locales/fr/LC_MESSAGES/plone.po
imio/zamqp/pm/profiles/default/imio_zamqp_pm_default_marker.txt
imio/zamqp/pm/profiles/default/import_steps.xml
imio/zamqp/pm/profiles/default/metadata.xml
imio/zamqp/pm/profiles/default/registry.xml
imio/zamqp/pm/profiles/testing/metadata.xml
imio/zamqp/pm/tests/__init__.py
imio/zamqp/pm/tests/base.py
imio/zamqp/pm/tests/file.pdf
imio/zamqp/pm/tests/file.txt
imio/zamqp/pm/tests/file_corrupt.pdf
imio/zamqp/pm/tests/test_consumer.py
imio/zamqp/pm/tests/test_overrides.py
imio/zamqp/pm/tests/test_utils.py
imio/zamqp/pm/tests/test_views.py
imio_zamqp_pm-0.19.dist-info/METADATA
imio_zamqp_pm-0.19.dist-info/WHEEL
imio_zamqp_pm-0.19.dist-info/entry_points.txt
imio_zamqp_pm-0.19.dist-info/namespace_packages.txt
imio_zamqp_pm-0.19.dist-info/top_level.txt
imio_zamqp_pm-0.19.dist-info/RECORD
