Metadata-Version: 2.4
Name: imio.zamqp.pm
Version: 0.19
Summary: PloneMeeting specific methods to use amqp
Home-page: https://github.com/imio/
Author: IMIO
Author-email: support@imio.be
License: GPL
Keywords: Plone Python IMIO
Classifier: Development Status :: 6 - Mature
Classifier: Environment :: Web Environment
Classifier: Framework :: Plone
Classifier: License :: OSI Approved :: GNU General Public License (GPL)
Classifier: Operating System :: OS Independent
Classifier: Programming Language :: Python
Classifier: Programming Language :: Python :: 2.7
Classifier: Topic :: Software Development :: Libraries :: Python Modules
Requires-Dist: setuptools
Requires-Dist: collective.dms.scanbehavior
Requires-Dist: imio.helpers[pdf]
Requires-Dist: imio.zamqp.core
Requires-Dist: Products.PloneMeeting
Provides-Extra: test
Requires-Dist: Products.PloneMeeting[test]; extra == "test"
Dynamic: author
Dynamic: author-email
Dynamic: classifier
Dynamic: description
Dynamic: home-page
Dynamic: keywords
Dynamic: license
Dynamic: provides-extra
Dynamic: requires-dist
Dynamic: summary
